tomso/__init__.py
tomso/adipls.py
tomso/cli.py
tomso/constants.py
tomso/fgong.py
tomso/gyre.py
tomso/mesa.py
tomso/stars.py
tomso/utils.py
tomso-0.2.1.data/scripts/tomso
tomso-0.2.1.dist-info/LICENSE
tomso-0.2.1.dist-info/METADATA
tomso-0.2.1.dist-info/WHEEL
tomso-0.2.1.dist-info/top_level.txt
tomso-0.2.1.dist-info/RECORD
