Metadata-Version: 2.1
Name: tomso
Version: 0.2.1
Summary: Tools for Models of Stars and their Oscillations
Home-page: https://github.com/warrickball/tomso
Download-URL: https://github.com/warrickball/tomso/archive/v0.2.1.tar.gz
Author: Warrick Ball
Author-email: W.H.Ball@bham.ac.uk
License: MIT
Classifier: License :: OSI Approved :: MIT License
Classifier: Programming Language :: Python
License-File: LICENSE
Requires-Dist: numpy
